{
        "type":    "minecraft:block",
        "pools":    [
                                    {
                                            "rolls":    1,
                                            "entries":    [
                                                                            {
                                                                                    "type":    "minecraft:item",
                                                                                    "name":    "immortal_cultivation_mod:star_dust_stone"
                                                                            }
                                                                    ],
                                            "conditions":    [
                                                                                 {
                                                                                         "condition":    "minecraft:survives_explosion"
                                                                                 }
                                                                         ]
                                    }
                            ]
}